address_templeter/__init__.py
address_templeter/city.py
address_templeter/context.py
address_templeter/house.py
address_templeter/learned_settings.crfsuite
address_templeter-1.41.dist-info/METADATA
address_templeter-1.41.dist-info/WHEEL
address_templeter-1.41.dist-info/top_level.txt
address_templeter-1.41.dist-info/RECORD
