Metadata-Version: 2.1
Name: address-templeter
Version: 1.41
Summary: search for addresses in the text
Home-page: https://github.com/Saylermb/Address_Templeter
License: The MIT License: http://www.opensource.org/licenses/mit-license.php
Platform: UNKNOWN
Classifier: Intended Audience :: Developers
Classifier: Intended Audience :: Science/Research
Classifier: License :: OSI Approved :: MIT License
Classifier: Natural Language :: Russian
Classifier: Topic :: Software Development :: Libraries :: Python Modules
Classifier: Topic :: Scientific/Engineering
Classifier: Topic :: Scientific/Engineering :: Information Analysis
Requires-Dist: python-crfsuite (>=0.9.6)
Requires-Dist: lxml
